LICENSE
MANIFEST.in
README.rst
setup.py
conf/example-conf
vol/__init__.py
vol/main.py
vol.egg-info/PKG-INFO
vol.egg-info/SOURCES.txt
vol.egg-info/dependency_links.txt
vol.egg-info/entry_points.txt
vol.egg-info/not-zip-safe
vol.egg-info/requires.txt
vol.egg-info/top_level.txt