Metadata-Version: 1.1
Name: vol
Version: 0.1.0
Summary: volume control in the shell for your mac
Home-page: https://github.com/bmaeser/vol
Author: Bernhard Maeser
Author-email: bernhard.maeser@gmail.com
License: MIT
Platform: UNKNOWN
Classifier: Development Status :: 4 - Beta
Classifier: Operating System :: MacOS :: MacOS X
Classifier: Intended Audience :: End Users/Desktop
Classifier: License :: OSI Approved :: MIT License
Classifier: Programming Language :: Python
Classifier: Programming Language :: Python :: 2.7
Classifier: Topic :: Multimedia :: Sound/Audio
Classifier: Topic :: Utilities
